bigdict/__init__.py
bigdict/_bigdict.py
bigdict/py.typed
bigdict-22.5.29.dist-info/LICENSE
bigdict-22.5.29.dist-info/WHEEL
bigdict-22.5.29.dist-info/METADATA
bigdict-22.5.29.dist-info/RECORD
