Metadata-Version: 2.1
Name: bigdict
Version: 22.5.29
Summary: Bigdict based on rocksdb
Author-email: Zepu Zhang <zepu.zhang@gmail.com>
Requires-Python: >=3.8
Classifier: Intended Audience :: Developers
Classifier: Programming Language :: Python :: 3
Classifier: Topic :: Software Development :: Libraries :: Python Modules
Requires-Dist: lbry-rocksdb
Requires-Dist: bandit ; extra == "test"
Requires-Dist: coverage[toml] ; extra == "test"
Requires-Dist: flake8 ; extra == "test"
Requires-Dist: mypy ; extra == "test"
Requires-Dist: pylint ; extra == "test"
Requires-Dist: pytest ; extra == "test"
Requires-Dist: pytest-asyncio ; extra == "test"
Project-URL: Source, https://github.com/zpz/bigdict
Provides-Extra: test
